refcatch/__init__.py
refcatch/cli.py
refcatch/core.py
refcatch-0.1.1.dist-info/LICENSE
refcatch-0.1.1.dist-info/METADATA
refcatch-0.1.1.dist-info/WHEEL
refcatch-0.1.1.dist-info/entry_points.txt
refcatch-0.1.1.dist-info/top_level.txt
refcatch-0.1.1.dist-info/RECORD
