Metadata-Version: 2.1
Name: refcatch
Version: 0.1.1
Summary: A package for processing academic references from plaintext files
Home-page: https://github.com/AhsanKhodami/refcatch
Author: Mohammad Ahsan Khodami
Author-email: Mohammad Ahsan Khodami <ahsan.khodami@gmail.com>
License: MIT License
Project-URL: Homepage, https://github.com/AhsanKhodami/refcatch
Project-URL: Bug Tracker, https://github.com/AhsanKhodami/refcatch/issues
Keywords: references,doi,academic,bibliography,citation
Classifier: Programming Language :: Python :: 3
Classifier: License :: OSI Approved :: MIT License
Classifier: Operating System :: OS Independent
Classifier: Topic :: Scientific/Engineering :: Information Analysis
Classifier: Topic :: Text Processing :: Markup :: Markdown
Classifier: Topic :: Utilities
Requires-Python: >=3.6
License-File: LICENSE
Requires-Dist: requests>=2.25.0
